pythfinder/__init__.py
pythfinder/character.py
pythfinder/collections.py
pythfinder/helpers.py
pythfinder/vars.py
pythfinder-0.19.0.dist-info/LICENSE
pythfinder-0.19.0.dist-info/METADATA
pythfinder-0.19.0.dist-info/WHEEL
pythfinder-0.19.0.dist-info/top_level.txt
pythfinder-0.19.0.dist-info/RECORD
