Metadata-Version: 2.1
Name: pythfinder
Version: 0.19.0
Summary: A pathfinder character sheet python package
Home-page: https://github.com/matthew-hale/pythfinder
Author: Matthew Hale
Author-email: matthew.hale@protonmail.com
License: UNKNOWN
Platform: UNKNOWN
Classifier: Programming Language :: Python :: 3
Classifier: License :: OSI Approved :: MIT License
Classifier: Operating System :: OS Independent
Requires-Python: >=3.6
